{
    "name": "svywebcam",
    "displayName": "svywebcam",
    "packageType": "Web-Component",
    "icon": "https://raw.githubusercontent.com/Servoy/svywebcam/master/icon.png",
    "description": "Utilize your webcam with the NGClient",
    "wikiUrl": "https://github.com/Servoy/svywebcam/wiki",
    "sourceUrl": "https://github.com/Servoy/svywebcam",
    "releases": [
    	{"version": "1.0.0","url": "https://github.com/Servoy/svywebcam/releases/download/1.0.0/svywebcam.zip","servoy-version":"8.1.1"},
    	{"version": "1.0.1","url": "https://github.com/Servoy/svywebcam/releases/download/1.0.1/svywebcam.zip","servoy-version":"8.1.1"},
    	{"version": "1.0.2","url": "https://github.com/Servoy/svywebcam/releases/download/1.0.2/svywebcam.zip","servoy-version":"8.1.1"},
    	{"version": "1.0.3","url": "https://github.com/Servoy/svywebcam/releases/download/1.0.3/svywebcam.zip","servoy-version":"8.1.1"},
    ]
}